{
  "id": "MAP_HALLOW_SPARK",
  "name": "HallowSpark",
  "layout": "LAYOUT_HALLOW_SPARK",
  "music": "MUS_ABANDONED_SHIP",
  "region_map_section": "MAPSEC_LITTLEROOT_TOWN",
  "requires_flash": false,
  "weather": "WEATHER_NONE",
  "map_type": "MAP_TYPE_CITY",
  "allow_cycling": true,
  "allow_escaping": false,
  "allow_running": true,
  "show_map_name": true,
  "battle_scene": "MAP_BATTLE_SCENE_NORMAL",
  "connections": [
    {
      "direction": "down",
      "offset": 10,
      "map": "MAP_ALPHA_PATHWAY"
    },
    {
      "direction": "left",
      "offset": -2,
      "map": "MAP_ROUTE4"
    }
  ],
  "object_events": [
    {
      "graphics_id": "OBJ_EVENT_GFX_AZURILL",
      "x": 9,
      "y": 30,
      "elevation": 3,
      "movement_type": "MOVEMENT_TYPE_LOOK_AROUND",
      "movement_range_x": 0,
      "movement_range_y": 0,
      "trainer_type": "TRAINER_TYPE_NONE",
      "trainer_sight_or_berry_tree_id": "0",
      "script": "Common_Pokemon_Reluctant_Move_Aside",
      "flag": "FLAG_UNBLOCK_HALLOW_SPARK"
    },
    {
      "graphics_id": "OBJ_EVENT_GFX_AZURILL",
      "x": 8,
      "y": 30,
      "elevation": 3,
      "movement_type": "MOVEMENT_TYPE_LOOK_AROUND",
      "movement_range_x": 0,
      "movement_range_y": 0,
      "trainer_type": "TRAINER_TYPE_NONE",
      "trainer_sight_or_berry_tree_id": "0",
      "script": "Common_Pokemon_Reluctant_Move_Aside",
      "flag": "FLAG_UNBLOCK_HALLOW_SPARK"
    },
    {
      "graphics_id": "OBJ_EVENT_GFX_ZIGZAGOON_2",
      "x": 7,
      "y": 31,
      "elevation": 3,
      "movement_type": "MOVEMENT_TYPE_LOOK_AROUND",
      "movement_range_x": 0,
      "movement_range_y": 0,
      "trainer_type": "TRAINER_TYPE_NONE",
      "trainer_sight_or_berry_tree_id": "0",
      "script": "Common_Pokemon_Reluctant_Move_Aside",
      "flag": "FLAG_UNBLOCK_HALLOW_SPARK"
    },
    {
      "graphics_id": "OBJ_EVENT_GFX_POOCHYENA",
      "x": 5,
      "y": 33,
      "elevation": 3,
      "movement_type": "MOVEMENT_TYPE_LOOK_AROUND",
      "movement_range_x": 0,
      "movement_range_y": 0,
      "trainer_type": "TRAINER_TYPE_NONE",
      "trainer_sight_or_berry_tree_id": "0",
      "script": "Common_Pokemon_Reluctant_Move_Aside",
      "flag": "FLAG_UNBLOCK_HALLOW_SPARK"
    },
    {
      "graphics_id": "OBJ_EVENT_GFX_SKITTY",
      "x": 6,
      "y": 31,
      "elevation": 3,
      "movement_type": "MOVEMENT_TYPE_LOOK_AROUND",
      "movement_range_x": 0,
      "movement_range_y": 0,
      "trainer_type": "TRAINER_TYPE_NONE",
      "trainer_sight_or_berry_tree_id": "0",
      "script": "Common_Pokemon_Reluctant_Move_Aside",
      "flag": "FLAG_UNBLOCK_HALLOW_SPARK"
    },
    {
      "graphics_id": "OBJ_EVENT_GFX_GSLOWPOKE",
      "x": 6,
      "y": 32,
      "elevation": 3,
      "movement_type": "MOVEMENT_TYPE_LOOK_AROUND",
      "movement_range_x": 0,
      "movement_range_y": 0,
      "trainer_type": "TRAINER_TYPE_NONE",
      "trainer_sight_or_berry_tree_id": "0",
      "script": "Common_Pokemon_Reluctant_Move_Aside",
      "flag": "FLAG_UNBLOCK_HALLOW_SPARK"
    }
  ],
  "warp_events": [

  ],
  "coord_events": [

  ],
  "bg_events": [

  ]
}
